authbwc/__init__.py
authbwc/commands.py
authbwc/events.py
authbwc/events.py~
authbwc/forms.py
authbwc/forms.py~
authbwc/grids.py
authbwc/grids.py~
authbwc/version.txt
authbwc/views.py
authbwc/views.py~
authbwc/config/__init__.py
authbwc/config/settings.py
authbwc/config/settings.py~
authbwc/helpers/__init__.py
authbwc/helpers/__init__.py~
authbwc/helpers/email.py
authbwc/helpers/email.py~
authbwc/helpers/functions.py
authbwc/helpers/functions.py~
authbwc/helpers/password.py
authbwc/helpers/session.py
authbwc/lib/__init__.py
authbwc/lib/testing.py
authbwc/lib/testing.py~
authbwc/model/__init__.py
authbwc/model/declarative.py
authbwc/model/declarative.py~
authbwc/model/metadata.py
authbwc/model/metadata.py~
authbwc/model/orm.py
authbwc/model/orm.py~
authbwc/model/queries.py
authbwc/model/queries.py~
authbwc/sql/fix_group_fk.sql
authbwc/tasks/__init__.py
authbwc/tasks/clear_db_data.py
authbwc/tasks/clear_db_data.py~
authbwc/tasks/fix_group_fk.py
authbwc/tasks/fix_group_fk.py~
authbwc/tasks/init_db.py
authbwc/templates/change_password.html
authbwc/templates/change_password_email.txt
authbwc/templates/crud_addedit.html
authbwc/templates/crud_addedit.js
authbwc/templates/dg_crud_manage.html
authbwc/templates/login.html
authbwc/templates/lost_password.html
authbwc/templates/new_user_email.txt
authbwc/templates/password_reset_email.txt
authbwc/templates/permission_manage.html
authbwc/templates/permission_map.css
authbwc/templates/permission_map.html
authbwc/templates/reset_password.html
authbwc/templates/user_profile.html
AuthBWC-0.3.3.dist-info/METADATA
AuthBWC-0.3.3.dist-info/WHEEL
AuthBWC-0.3.3.dist-info/entry_points.txt
AuthBWC-0.3.3.dist-info/top_level.txt
AuthBWC-0.3.3.dist-info/RECORD
