Metadata-Version: 2.1
Name: AuthBWC
Version: 0.3.3
Summary: A user authentication and authorization component for the BlazeWeb framework
Home-page: https://github.com/blazelibs/authbwc/
Author: Randy Syring
Author-email: randy.syring@level12.io
License: BSD
Platform: UNKNOWN
Classifier: Development Status :: 4 - Beta
Classifier: Intended Audience :: Developers
Classifier: License :: OSI Approved :: BSD License
Classifier: Operating System :: OS Independent
Classifier: Programming Language :: Python :: 2.7
Classifier: Programming Language :: Python :: 3.4
Classifier: Programming Language :: Python :: 3.5
Classifier: Topic :: Internet :: WWW/HTTP
Requires-Dist: CommonBWC (>=0.1.0)
Requires-Dist: WebGrid (>=0.1.6)
Requires-Dist: BlazeWeb (>=0.3.1)
Requires-Dist: SQLAlchemyBWC
Requires-Dist: TemplatingBWC (>=0.3.0)
Requires-Dist: six
Provides-Extra: dev
Requires-Dist: codecov; extra == 'dev'
Requires-Dist: coverage; extra == 'dev'
Requires-Dist: flake8; extra == 'dev'
Requires-Dist: minimock; extra == 'dev'
Requires-Dist: nose; extra == 'dev'
Requires-Dist: pyquery; extra == 'dev'
Requires-Dist: tox; extra == 'dev'
Requires-Dist: webtest; extra == 'dev'
Requires-Dist: wheel; extra == 'dev'
